odoo/addons/partner_sequence_address_type/README.rst
odoo/addons/partner_sequence_address_type/__init__.py
odoo/addons/partner_sequence_address_type/__manifest__.py
odoo/addons/partner_sequence_address_type/hooks.py
odoo/addons/partner_sequence_address_type/i18n/es.po
odoo/addons/partner_sequence_address_type/i18n/it.po
odoo/addons/partner_sequence_address_type/i18n/partner_sequence_address_type.pot
odoo/addons/partner_sequence_address_type/models/__init__.py
odoo/addons/partner_sequence_address_type/models/res_partner.py
odoo/addons/partner_sequence_address_type/models/res_partner_sequence_type.py
odoo/addons/partner_sequence_address_type/readme/CONTRIBUTORS.rst
odoo/addons/partner_sequence_address_type/readme/DESCRIPTION.rst
odoo/addons/partner_sequence_address_type/readme/USAGE.rst
odoo/addons/partner_sequence_address_type/security/ir.model.access.csv
odoo/addons/partner_sequence_address_type/static/description/icon.png
odoo/addons/partner_sequence_address_type/static/description/index.html
odoo/addons/partner_sequence_address_type/views/ir_sequence_views.xml
odoo/addons/partner_sequence_address_type/views/res_partner_views.xml
odoo14_addon_partner_sequence_address_type-14.0.1.0.1.dev7.dist-info/METADATA
odoo14_addon_partner_sequence_address_type-14.0.1.0.1.dev7.dist-info/WHEEL
odoo14_addon_partner_sequence_address_type-14.0.1.0.1.dev7.dist-info/top_level.txt
odoo14_addon_partner_sequence_address_type-14.0.1.0.1.dev7.dist-info/RECORD
